MANIFEST.in
README.md
requirements.txt
setup.py
brainpp_yl/__info__.py
brainpp_yl/__init__.py
brainpp_yl/check_nori.py
brainpp_yl/env.py
brainpp_yl/fs.py
brainpp_yl/pytorch.py
brainpp_yl/tools.py
brainpp_yl.egg-info/PKG-INFO
brainpp_yl.egg-info/SOURCES.txt
brainpp_yl.egg-info/dependency_links.txt
brainpp_yl.egg-info/requires.txt
brainpp_yl.egg-info/top_level.txt
test/test_fs_for_zip_tar.py